aws_error_utils/__init__.py
aws_error_utils/aws_error_utils.py
aws_error_utils/py.typed
aws_error_utils-2.7.0.dist-info/LICENSE
aws_error_utils-2.7.0.dist-info/WHEEL
aws_error_utils-2.7.0.dist-info/METADATA
aws_error_utils-2.7.0.dist-info/RECORD
