Metadata-Version: 2.1
Name: aws-error-utils
Version: 2.7.0
Summary: Error-handling functions for boto3/botocore
Home-page: https://github.com/benkehoe/aws-error-utils
License: Apache-2.0
Author: Ben Kehoe
Requires-Python: >=3.7,<4
Classifier: Development Status :: 5 - Production/Stable
Classifier: Intended Audience :: Developers
Classifier: Intended Audience :: System Administrators
Classifier: License :: OSI Approved :: Apache Software License
Classifier: Operating System :: OS Independent
Classifier: Programming Language :: Python :: 3
Classifier: Programming Language :: Python :: 3.7
Classifier: Programming Language :: Python :: 3.8
Classifier: Programming Language :: Python :: 3.9
Classifier: Programming Language :: Python :: 3.10
Classifier: Programming Language :: Python :: 3.11
Classifier: Topic :: Utilities
Requires-Dist: botocore
Project-URL: Repository, https://github.com/benkehoe/aws-error-utils
